ministat/__init__.py
ministat/ministat.py
ministat-0.0.2.dist-info/DESCRIPTION.rst
ministat-0.0.2.dist-info/METADATA
ministat-0.0.2.dist-info/RECORD
ministat-0.0.2.dist-info/WHEEL
ministat-0.0.2.dist-info/metadata.json
ministat-0.0.2.dist-info/top_level.txt
