Metadata-Version: 2.0
Name: ministat
Version: 0.0.2
Summary: A mini statistics library for Python inspired by the `ministat` command
Home-page: https://github.com/lebinh/ministat
Author: Binh Le
Author-email: lebinh.it@gmail.com
License: MIT
Keywords: ministat statistic
Platform: UNKNOWN
Classifier: Development Status :: 3 - Alpha
Classifier: Intended Audience :: Developers
Classifier: License :: OSI Approved :: MIT License
Classifier: Programming Language :: Python :: 2
Classifier: Programming Language :: Python :: 2.6
Classifier: Programming Language :: Python :: 2.7
Classifier: Programming Language :: Python :: 3
Classifier: Programming Language :: Python :: 3.3
Classifier: Programming Language :: Python :: 3.4
Classifier: Programming Language :: Python :: 3.5
Provides-Extra: dev
Provides-Extra: test
